translate_pptx/__init__.py
translate_pptx/_endpoints.py
translate_pptx/_pptx.py
translate_pptx/_terminal.py
translate_pptx/_translation.py
translate_pptx/_utilities.py
translate_pptx-0.1.1.dist-info/LICENSE
translate_pptx-0.1.1.dist-info/METADATA
translate_pptx-0.1.1.dist-info/WHEEL
translate_pptx-0.1.1.dist-info/entry_points.txt
translate_pptx-0.1.1.dist-info/top_level.txt
translate_pptx-0.1.1.dist-info/RECORD
